pytaxon/__init__.py
pytaxon/main.py
pytaxon/pytaxon.py
pytaxon/pytaxon_gui.py
pytaxon/assets/pytaxon_logo.png
pytaxon-5.0.9.dist-info/METADATA
pytaxon-5.0.9.dist-info/WHEEL
pytaxon-5.0.9.dist-info/entry_points.txt
pytaxon-5.0.9.dist-info/top_level.txt
pytaxon-5.0.9.dist-info/RECORD
