Metadata-Version: 2.1
Name: pytaxon
Version: 5.0.9
Summary: Pytaxon é uma aplicação open source de auxílio à pesquisa para identificação de erros e correção de nomenclatura taxonômica das espécies da biodiversidade
Home-page: https://github.com/pytaxon
Author: Marco Aurélio Proença Neto, Marcos Paulo Alves de Sousa
Author-email: desousa.mpa@gmail.com
License: MIT License
Keywords: pytaxon
Requires-Dist: pandas
Requires-Dist: openpyxl
Requires-Dist: tqdm
Requires-Dist: xlrd
Requires-Dist: requests
Requires-Dist: argparse
Requires-Dist: Jinja2
Requires-Dist: ttkthemes
Requires-Dist: tk
Requires-Dist: matplotlib
Requires-Dist: customtkinter
Requires-Dist: CTkMessagebox
Requires-Dist: setuptools
